pip_services4_observability/__init__.py
pip_services4_observability/build/DefaultObservabilityFactory.py
pip_services4_observability/build/__init__.py
pip_services4_observability/count/CachedCounters.py
pip_services4_observability/count/CompositeCounters.py
pip_services4_observability/count/Counter.py
pip_services4_observability/count/CounterTiming.py
pip_services4_observability/count/CounterType.py
pip_services4_observability/count/DefaultCountersFactory.py
pip_services4_observability/count/ICounterTimingCallback.py
pip_services4_observability/count/ICounters.py
pip_services4_observability/count/LogCounters.py
pip_services4_observability/count/NullCounters.py
pip_services4_observability/count/__init__.py
pip_services4_observability/log/CachedLogger.py
pip_services4_observability/log/CompositeLogger.py
pip_services4_observability/log/ConsoleLogger.py
pip_services4_observability/log/DefaultLoggerFactory.py
pip_services4_observability/log/ILogger.py
pip_services4_observability/log/LogLevel.py
pip_services4_observability/log/LogLevelConverter.py
pip_services4_observability/log/LogMessage.py
pip_services4_observability/log/Logger.py
pip_services4_observability/log/NullLogger.py
pip_services4_observability/log/__init__.py
pip_services4_observability/trace/CachedTracer.py
pip_services4_observability/trace/CompositeTracer.py
pip_services4_observability/trace/DefaultTracerFactory.py
pip_services4_observability/trace/ITracer.py
pip_services4_observability/trace/LogTracer.py
pip_services4_observability/trace/NullTracer.py
pip_services4_observability/trace/OperationTrace.py
pip_services4_observability/trace/TraceTiming.py
pip_services4_observability/trace/__init__.py
pip_services4_observability-0.0.5.dist-info/LICENSE
pip_services4_observability-0.0.5.dist-info/METADATA
pip_services4_observability-0.0.5.dist-info/WHEEL
pip_services4_observability-0.0.5.dist-info/top_level.txt
pip_services4_observability-0.0.5.dist-info/zip-safe
pip_services4_observability-0.0.5.dist-info/RECORD
